crm_benchmark_lib/__init__.py
crm_benchmark_lib/client.py
crm_benchmark_lib/examples/__init__.py
crm_benchmark_lib/examples/simple_agent.py
crm_benchmark_lib/tests/__init__.py
crm_benchmark_lib/tests/test_client.py
crm_benchmark_lib-0.2.1.dist-info/METADATA
crm_benchmark_lib-0.2.1.dist-info/WHEEL
crm_benchmark_lib-0.2.1.dist-info/top_level.txt
crm_benchmark_lib-0.2.1.dist-info/RECORD
