Metadata-Version: 2.4
Name: crm-benchmark-lib
Version: 0.2.1
Summary: Client library for the CRM AI Agent Benchmarking API
Home-page: https://github.com/aiagentchallenge/crm-benchmark-lib
Author: CRM Benchmark Team
Author-email: info@aiagentchallenge.com
Classifier: Programming Language :: Python :: 3
Classifier: License :: OSI Approved :: MIT License
Classifier: Operating System :: OS Independent
Requires-Python: >=3.7
Requires-Dist: requests>=2.25.0
Requires-Dist: pandas>=1.1.0
Requires-Dist: tqdm>=4.50.0
Dynamic: author
Dynamic: author-email
Dynamic: classifier
Dynamic: description
Dynamic: description-content-type
Dynamic: home-page
Dynamic: requires-dist
Dynamic: requires-python
Dynamic: summary
